LICENSE
README.md
dataops_toolkits/__init__.py
dataops_toolkits/io.py
dataops_toolkits/scripts/adduuid.py
dataops_toolkits/scripts/jsonconvert.py
dataops_toolkits/utils.py
dataops_toolkits-0.1.2.dist-info/entry_points.txt
dataops_toolkits-0.1.2.dist-info/LICENSE
dataops_toolkits-0.1.2.dist-info/WHEEL
dataops_toolkits-0.1.2.dist-info/METADATA
dataops_toolkits-0.1.2.dist-info/RECORD
