Metadata-Version: 2.1
Name: dataops-toolkits
Version: 0.1.2
Summary: Gadget Collection of DataOps in MLOps
Home-page: https://github.com/yuiant/dataops
License: MIT
Author: yuiant
Author-email: gyuiant@gmail.com
Requires-Python: >=3.7,<4.0
Classifier: License :: OSI Approved :: MIT License
Classifier: Programming Language :: Python :: 3
Classifier: Programming Language :: Python :: 3.10
Classifier: Programming Language :: Python :: 3.7
Classifier: Programming Language :: Python :: 3.8
Classifier: Programming Language :: Python :: 3.9
Requires-Dist: label-studio (==1.5.0)
Project-URL: Repository, https://github.com/yuiant/dataops
